sphinxarg/__init__.py
sphinxarg/ext.py
sphinxarg/markdown.py
sphinxarg/parser.py
sphinx_argparse_ru-0.3.1.dist-info/LICENSE
sphinx_argparse_ru-0.3.1.dist-info/WHEEL
sphinx_argparse_ru-0.3.1.dist-info/METADATA
sphinx_argparse_ru-0.3.1.dist-info/RECORD
