Metadata-Version: 2.1
Name: sphinx-argparse-ru
Version: 0.3.1
Summary: A sphinx extension that automatically documents argparse commands and options
Home-page: https://github.com/imercury13/sphinx-argparse-ru
License: MIT
Author: Ash Berlin-Taylor
Author-email: ash_github@firemirror.com
Requires-Python: >=3.6
Classifier: Framework :: Sphinx :: Extension
Classifier: License :: OSI Approved :: MIT License
Classifier: Programming Language :: Python :: 3
Classifier: Programming Language :: Python :: 3.6
Classifier: Programming Language :: Python :: 3.7
Classifier: Programming Language :: Python :: 3.8
Classifier: Programming Language :: Python :: 3.9
Classifier: Programming Language :: Python :: 3.10
Provides-Extra: markdown
Requires-Dist: CommonMark (>=0.5.6); extra == "markdown"
Requires-Dist: sphinx (>=1.2.0)
Project-URL: Repository, https://github.com/imercury13/sphinx-argparse-ru
